rlbot_lua.cp37-win_amd64.pyd
rlbot_lua-0.1.5.dist-info/LICENSE
rlbot_lua-0.1.5.dist-info/METADATA
rlbot_lua-0.1.5.dist-info/WHEEL
rlbot_lua-0.1.5.dist-info/top_level.txt
rlbot_lua-0.1.5.dist-info/RECORD
