Metadata-Version: 2.1
Name: rlbot-lua
Version: 0.1.5
Summary: Lua wrapper for RLBot
Home-page: https://github.com/martmists/RLBot_Lua
Author: Martmists
Author-email: mail@martmists.com
License: MIT
Keywords: rlbot,lua,cpp,extension
Platform: UNKNOWN
Classifier: Development Status :: 4 - Beta
Classifier: Intended Audience :: Developers
Classifier: License :: OSI Approved :: MIT License
Classifier: Operating System :: OS Independent
Classifier: Programming Language :: Python :: 3 :: Only
Classifier: Programming Language :: Python :: Implementation :: CPython
Classifier: Topic :: Games/Entertainment
Classifier: Topic :: Software Development :: Libraries :: Python Modules
Requires-Dist: rlbot
